{
    "tag-fifa-19": {
        "23 Apr  2019": {
            "v": "19",
            "e": "159437",
            "set": "true",
            "uri": "v=19&e=159437&set=true"
        },
        "18 Apr  2019": {
            "v": "19",
            "e": "159432",
            "set": "true",
            "uri": "v=19&e=159432&set=true"
        },
        "16 Apr  2019": {
            "v": "19",
            "e": "159430",
            "set": "true",
            "uri": "v=19&e=159430&set=true"
        },
        "15 Apr  2019": {
            "v": "19",
            "e": "159429",
            "set": "true",
            "uri": "v=19&e=159429&set=true"
        },
        "11 Apr  2019": {
            "v": "19",
            "e": "159425",
            "set": "true",
            "uri": "v=19&e=159425&set=true"
        },
        "08 Apr  2019": {
            "v": "19",
            "e": "159422",
            "set": "true",
            "uri": "v=19&e=159422&set=true"
        },
        "04 Apr  2019": {
            "v": "19",
            "e": "159418",
            "set": "true",
            "uri": "v=19&e=159418&set=true"
        },
        "01 Apr  2019": {
            "v": "19",
            "e": "159415",
            "set": "true",
            "uri": "v=19&e=159415&set=true"
        },
        "28 Mar  2019": {
            "v": "19",
            "e": "159411",
            "set": "true",
            "uri": "v=19&e=159411&set=true"
        },
        "25 Mar  2019": {
            "v": "19",
            "e": "159408",
            "set": "true",
            "uri": "v=19&e=159408&set=true"
        },
        "21 Mar  2019": {
            "v": "19",
            "e": "159404",
            "set": "true",
            "uri": "v=19&e=159404&set=true"
        },
        "20 Mar  2019": {
            "v": "19",
            "e": "159403",
            "set": "true",
            "uri": "v=19&e=159403&set=true"
        },
        "18 Mar  2019": {
            "v": "19",
            "e": "159401",
            "set": "true",
            "uri": "v=19&e=159401&set=true"
        },
        "14 Mar  2019": {
            "v": "19",
            "e": "159397",
            "set": "true",
            "uri": "v=19&e=159397&set=true"
        },
        "04 Mar  2019": {
            "v": "19",
            "e": "159387",
            "set": "true",
            "uri": "v=19&e=159387&set=true"
        },
        "28 Feb  2019": {
            "v": "19",
            "e": "159383",
            "set": "true",
            "uri": "v=19&e=159383&set=true"
        },
        "22 Feb  2019": {
            "v": "19",
            "e": "159377",
            "set": "true",
            "uri": "v=19&e=159377&set=true"
        },
        "21 Feb  2019": {
            "v": "19",
            "e": "159376",
            "set": "true",
            "uri": "v=19&e=159376&set=true"
        },
        "14 Feb  2019": {
            "v": "19",
            "e": "159369",
            "set": "true",
            "uri": "v=19&e=159369&set=true"
        },
        "11 Feb  2019": {
            "v": "19",
            "e": "159366",
            "set": "true",
            "uri": "v=19&e=159366&set=true"
        },
        "07 Feb  2019": {
            "v": "19",
            "e": "159362",
            "set": "true",
            "uri": "v=19&e=159362&set=true"
        },
        "04 Feb  2019": {
            "v": "19",
            "e": "159359",
            "set": "true",
            "uri": "v=19&e=159359&set=true"
        },
        "31 Jan  2019": {
            "v": "19",
            "e": "159355",
            "set": "true",
            "uri": "v=19&e=159355&set=true"
        },
        "28 Jan  2019": {
            "v": "19",
            "e": "159352",
            "set": "true",
            "uri": "v=19&e=159352&set=true"
        },
        "24 Jan  2019": {
            "v": "19",
            "e": "159348",
            "set": "true",
            "uri": "v=19&e=159348&set=true"
        },
        "21 Jan  2019": {
            "v": "19",
            "e": "159345",
            "set": "true",
            "uri": "v=19&e=159345&set=true"
        },
        "17 Jan  2019": {
            "v": "19",
            "e": "159341",
            "set": "true",
            "uri": "v=19&e=159341&set=true"
        },
        "14 Jan  2019": {
            "v": "19",
            "e": "159338",
            "set": "true",
            "uri": "v=19&e=159338&set=true"
        },
        "10 Jan  2019": {
            "v": "19",
            "e": "159334",
            "set": "true",
            "uri": "v=19&e=159334&set=true"
        },
        "07 Jan  2019": {
            "v": "19",
            "e": "159331",
            "set": "true",
            "uri": "v=19&e=159331&set=true"
        },
        "03 Jan  2019": {
            "v": "19",
            "e": "159327",
            "set": "true",
            "uri": "v=19&e=159327&set=true"
        },
        "27 Dec  2018": {
            "v": "19",
            "e": "159320",
            "set": "true",
            "uri": "v=19&e=159320&set=true"
        },
        "20 Dec  2018": {
            "v": "19",
            "e": "159313",
            "set": "true",
            "uri": "v=19&e=159313&set=true"
        },
        "17 Dec  2018": {
            "v": "19",
            "e": "159310",
            "set": "true",
            "uri": "v=19&e=159310&set=true"
        },
        "13 Dec  2018": {
            "v": "19",
            "e": "159306",
            "set": "true",
            "uri": "v=19&e=159306&set=true"
        },
        "03 Dec  2018": {
            "v": "19",
            "e": "159296",
            "set": "true",
            "uri": "v=19&e=159296&set=true"
        },
        "26 Nov  2018": {
            "v": "19",
            "e": "159289",
            "set": "true",
            "uri": "v=19&e=159289&set=true"
        },
        "15 Nov  2018": {
            "v": "19",
            "e": "159278",
            "set": "true",
            "uri": "v=19&e=159278&set=true"
        },
        "13 Nov  2018": {
            "v": "19",
            "e": "159276",
            "set": "true",
            "uri": "v=19&e=159276&set=true"
        },
        "05 Nov  2018": {
            "v": "19",
            "e": "159268",
            "set": "true",
            "uri": "v=19&e=159268&set=true"
        },
        "01 Nov  2018": {
            "v": "19",
            "e": "159264",
            "set": "true",
            "uri": "v=19&e=159264&set=true"
        },
        "29 Oct  2018": {
            "v": "19",
            "e": "159261",
            "set": "true",
            "uri": "v=19&e=159261&set=true"
        },
        "25 Oct  2018": {
            "v": "19",
            "e": "159257",
            "set": "true",
            "uri": "v=19&e=159257&set=true"
        },
        "23 Oct  2018": {
            "v": "19",
            "e": "159255",
            "set": "true",
            "uri": "v=19&e=159255&set=true"
        },
        "22 Oct  2018": {
            "v": "19",
            "e": "159254",
            "set": "true",
            "uri": "v=19&e=159254&set=true"
        },
        "18 Oct  2018": {
            "v": "19",
            "e": "159250",
            "set": "true",
            "uri": "v=19&e=159250&set=true"
        },
        "15 Oct  2018": {
            "v": "19",
            "e": "159247",
            "set": "true",
            "uri": "v=19&e=159247&set=true"
        },
        "11 Oct  2018": {
            "v": "19",
            "e": "159243",
            "set": "true",
            "uri": "v=19&e=159243&set=true"
        },
        "09 Oct  2018": {
            "v": "19",
            "e": "159241",
            "set": "true",
            "uri": "v=19&e=159241&set=true"
        },
        "04 Oct  2018": {
            "v": "19",
            "e": "159236",
            "set": "true",
            "uri": "v=19&e=159236&set=true"
        },
        "01 Oct  2018": {
            "v": "19",
            "e": "159233",
            "set": "true",
            "uri": "v=19&e=159233&set=true"
        },
        "27 Sep  2018": {
            "v": "19",
            "e": "159229",
            "set": "true",
            "uri": "v=19&e=159229&set=true"
        },
        "24 Sep  2018": {
            "v": "19",
            "e": "159226",
            "set": "true",
            "uri": "v=19&e=159226&set=true"
        },
        "20 Sep  2018": {
            "v": "19",
            "e": "159222",
            "set": "true",
            "uri": "v=19&e=159222&set=true"
        },
        "21 Aug  2018": {
            "v": "19",
            "e": "159192",
            "set": "true",
            "uri": "v=19&e=159192&set=true"
        },
        "19 Jul  2018": {
            "v": "19",
            "e": "159159",
            "set": "true",
            "uri": "v=19&e=159159&set=true"
        }
    },
    "tag-fifa-18": {
        "12 Sep  2018": {
            "v": "18",
            "e": "159214",
            "set": "true",
            "uri": "v=18&e=159214&set=true"
        },
        "06 Sep  2018": {
            "v": "18",
            "e": "159208",
            "set": "true",
            "uri": "v=18&e=159208&set=true"
        },
        "30 Aug  2018": {
            "v": "18",
            "e": "159201",
            "set": "true",
            "uri": "v=18&e=159201&set=true"
        },
        "23 Aug  2018": {
            "v": "18",
            "e": "159194",
            "set": "true",
            "uri": "v=18&e=159194&set=true"
        },
        "03 Aug  2018": {
            "v": "18",
            "e": "159174",
            "set": "true",
            "uri": "v=18&e=159174&set=true"
        },
        "26 Jul  2018": {
            "v": "18",
            "e": "159166",
            "set": "true",
            "uri": "v=18&e=159166&set=true"
        },
        "19 Jul  2018": {
            "v": "18",
            "e": "159159",
            "set": "true",
            "uri": "v=18&e=159159&set=true"
        },
        "14 Jun  2018": {
            "v": "18",
            "e": "159124",
            "set": "true",
            "uri": "v=18&e=159124&set=true"
        },
        "11 Jun  2018": {
            "v": "18",
            "e": "159121",
            "set": "true",
            "uri": "v=18&e=159121&set=true"
        },
        "07 Jun  2018": {
            "v": "18",
            "e": "159117",
            "set": "true",
            "uri": "v=18&e=159117&set=true"
        },
        "04 Jun  2018": {
            "v": "18",
            "e": "159114",
            "set": "true",
            "uri": "v=18&e=159114&set=true"
        },
        "31 May  2018": {
            "v": "18",
            "e": "159110",
            "set": "true",
            "uri": "v=18&e=159110&set=true"
        },
        "28 May  2018": {
            "v": "18",
            "e": "159107",
            "set": "true",
            "uri": "v=18&e=159107&set=true"
        },
        "24 May  2018": {
            "v": "18",
            "e": "159103",
            "set": "true",
            "uri": "v=18&e=159103&set=true"
        },
        "22 May  2018": {
            "v": "18",
            "e": "159101",
            "set": "true",
            "uri": "v=18&e=159101&set=true"
        },
        "17 May  2018": {
            "v": "18",
            "e": "159096",
            "set": "true",
            "uri": "v=18&e=159096&set=true"
        },
        "14 May  2018": {
            "v": "18",
            "e": "159093",
            "set": "true",
            "uri": "v=18&e=159093&set=true"
        },
        "10 May  2018": {
            "v": "18",
            "e": "159089",
            "set": "true",
            "uri": "v=18&e=159089&set=true"
        },
        "08 May  2018": {
            "v": "18",
            "e": "159087",
            "set": "true",
            "uri": "v=18&e=159087&set=true"
        },
        "03 May  2018": {
            "v": "18",
            "e": "159082",
            "set": "true",
            "uri": "v=18&e=159082&set=true"
        },
        "30 Apr  2018": {
            "v": "18",
            "e": "159079",
            "set": "true",
            "uri": "v=18&e=159079&set=true"
        },
        "26 Apr  2018": {
            "v": "18",
            "e": "159075",
            "set": "true",
            "uri": "v=18&e=159075&set=true"
        },
        "23 Apr  2018": {
            "v": "18",
            "e": "159072",
            "set": "true",
            "uri": "v=18&e=159072&set=true"
        },
        "19 Apr  2018": {
            "v": "18",
            "e": "159068",
            "set": "true",
            "uri": "v=18&e=159068&set=true"
        },
        "16 Apr  2018": {
            "v": "18",
            "e": "159065",
            "set": "true",
            "uri": "v=18&e=159065&set=true"
        },
        "12 Apr  2018": {
            "v": "18",
            "e": "159061",
            "set": "true",
            "uri": "v=18&e=159061&set=true"
        },
        "09 Apr  2018": {
            "v": "18",
            "e": "159058",
            "set": "true",
            "uri": "v=18&e=159058&set=true"
        },
        "05 Apr  2018": {
            "v": "18",
            "e": "159054",
            "set": "true",
            "uri": "v=18&e=159054&set=true"
        },
        "03 Apr  2018": {
            "v": "18",
            "e": "159052",
            "set": "true",
            "uri": "v=18&e=159052&set=true"
        },
        "29 Mar  2018": {
            "v": "18",
            "e": "159047",
            "set": "true",
            "uri": "v=18&e=159047&set=true"
        },
        "26 Mar  2018": {
            "v": "18",
            "e": "159044",
            "set": "true",
            "uri": "v=18&e=159044&set=true"
        },
        "22 Mar  2018": {
            "v": "18",
            "e": "159040",
            "set": "true",
            "uri": "v=18&e=159040&set=true"
        },
        "19 Mar  2018": {
            "v": "18",
            "e": "159037",
            "set": "true",
            "uri": "v=18&e=159037&set=true"
        },
        "15 Mar  2018": {
            "v": "18",
            "e": "159033",
            "set": "true",
            "uri": "v=18&e=159033&set=true"
        },
        "12 Mar  2018": {
            "v": "18",
            "e": "159030",
            "set": "true",
            "uri": "v=18&e=159030&set=true"
        },
        "08 Mar  2018": {
            "v": "18",
            "e": "159026",
            "set": "true",
            "uri": "v=18&e=159026&set=true"
        },
        "05 Mar  2018": {
            "v": "18",
            "e": "159023",
            "set": "true",
            "uri": "v=18&e=159023&set=true"
        },
        "01 Mar  2018": {
            "v": "18",
            "e": "159019",
            "set": "true",
            "uri": "v=18&e=159019&set=true"
        },
        "26 Feb  2018": {
            "v": "18",
            "e": "159016",
            "set": "true",
            "uri": "v=18&e=159016&set=true"
        },
        "22 Feb  2018": {
            "v": "18",
            "e": "159012",
            "set": "true",
            "uri": "v=18&e=159012&set=true"
        },
        "19 Feb  2018": {
            "v": "18",
            "e": "159009",
            "set": "true",
            "uri": "v=18&e=159009&set=true"
        },
        "15 Feb  2018": {
            "v": "18",
            "e": "159005",
            "set": "true",
            "uri": "v=18&e=159005&set=true"
        },
        "12 Feb  2018": {
            "v": "18",
            "e": "159002",
            "set": "true",
            "uri": "v=18&e=159002&set=true"
        },
        "08 Feb  2018": {
            "v": "18",
            "e": "158998",
            "set": "true",
            "uri": "v=18&e=158998&set=true"
        },
        "05 Feb  2018": {
            "v": "18",
            "e": "158995",
            "set": "true",
            "uri": "v=18&e=158995&set=true"
        },
        "01 Feb  2018": {
            "v": "18",
            "e": "158991",
            "set": "true",
            "uri": "v=18&e=158991&set=true"
        },
        "29 Jan  2018": {
            "v": "18",
            "e": "158988",
            "set": "true",
            "uri": "v=18&e=158988&set=true"
        },
        "25 Jan  2018": {
            "v": "18",
            "e": "158984",
            "set": "true",
            "uri": "v=18&e=158984&set=true"
        },
        "22 Jan  2018": {
            "v": "18",
            "e": "158981",
            "set": "true",
            "uri": "v=18&e=158981&set=true"
        },
        "18 Jan  2018": {
            "v": "18",
            "e": "158977",
            "set": "true",
            "uri": "v=18&e=158977&set=true"
        },
        "15 Jan  2018": {
            "v": "18",
            "e": "158974",
            "set": "true",
            "uri": "v=18&e=158974&set=true"
        },
        "11 Jan  2018": {
            "v": "18",
            "e": "158970",
            "set": "true",
            "uri": "v=18&e=158970&set=true"
        },
        "08 Jan  2018": {
            "v": "18",
            "e": "158967",
            "set": "true",
            "uri": "v=18&e=158967&set=true"
        },
        "04 Jan  2018": {
            "v": "18",
            "e": "158963",
            "set": "true",
            "uri": "v=18&e=158963&set=true"
        },
        "02 Jan  2018": {
            "v": "18",
            "e": "158961",
            "set": "true",
            "uri": "v=18&e=158961&set=true"
        },
        "28 Dec  2017": {
            "v": "18",
            "e": "158956",
            "set": "true",
            "uri": "v=18&e=158956&set=true"
        },
        "21 Dec  2017": {
            "v": "18",
            "e": "158949",
            "set": "true",
            "uri": "v=18&e=158949&set=true"
        },
        "18 Dec  2017": {
            "v": "18",
            "e": "158946",
            "set": "true",
            "uri": "v=18&e=158946&set=true"
        },
        "14 Dec  2017": {
            "v": "18",
            "e": "158942",
            "set": "true",
            "uri": "v=18&e=158942&set=true"
        },
        "11 Dec  2017": {
            "v": "18",
            "e": "158939",
            "set": "true",
            "uri": "v=18&e=158939&set=true"
        },
        "07 Dec  2017": {
            "v": "18",
            "e": "158935",
            "set": "true",
            "uri": "v=18&e=158935&set=true"
        },
        "04 Dec  2017": {
            "v": "18",
            "e": "158932",
            "set": "true",
            "uri": "v=18&e=158932&set=true"
        },
        "30 Nov  2017": {
            "v": "18",
            "e": "158928",
            "set": "true",
            "uri": "v=18&e=158928&set=true"
        },
        "27 Nov  2017": {
            "v": "18",
            "e": "158925",
            "set": "true",
            "uri": "v=18&e=158925&set=true"
        },
        "23 Nov  2017": {
            "v": "18",
            "e": "158921",
            "set": "true",
            "uri": "v=18&e=158921&set=true"
        },
        "20 Nov  2017": {
            "v": "18",
            "e": "158918",
            "set": "true",
            "uri": "v=18&e=158918&set=true"
        },
        "16 Nov  2017": {
            "v": "18",
            "e": "158914",
            "set": "true",
            "uri": "v=18&e=158914&set=true"
        },
        "13 Nov  2017": {
            "v": "18",
            "e": "158911",
            "set": "true",
            "uri": "v=18&e=158911&set=true"
        },
        "06 Nov  2017": {
            "v": "18",
            "e": "158904",
            "set": "true",
            "uri": "v=18&e=158904&set=true"
        },
        "02 Nov  2017": {
            "v": "18",
            "e": "158900",
            "set": "true",
            "uri": "v=18&e=158900&set=true"
        },
        "30 Oct  2017": {
            "v": "18",
            "e": "158897",
            "set": "true",
            "uri": "v=18&e=158897&set=true"
        },
        "26 Oct  2017": {
            "v": "18",
            "e": "158893",
            "set": "true",
            "uri": "v=18&e=158893&set=true"
        },
        "23 Oct  2017": {
            "v": "18",
            "e": "158890",
            "set": "true",
            "uri": "v=18&e=158890&set=true"
        },
        "19 Oct  2017": {
            "v": "18",
            "e": "158886",
            "set": "true",
            "uri": "v=18&e=158886&set=true"
        },
        "16 Oct  2017": {
            "v": "18",
            "e": "158883",
            "set": "true",
            "uri": "v=18&e=158883&set=true"
        },
        "12 Oct  2017": {
            "v": "18",
            "e": "158879",
            "set": "true",
            "uri": "v=18&e=158879&set=true"
        },
        "09 Oct  2017": {
            "v": "18",
            "e": "158876",
            "set": "true",
            "uri": "v=18&e=158876&set=true"
        },
        "05 Oct  2017": {
            "v": "18",
            "e": "158872",
            "set": "true",
            "uri": "v=18&e=158872&set=true"
        },
        "02 Oct  2017": {
            "v": "18",
            "e": "158869",
            "set": "true",
            "uri": "v=18&e=158869&set=true"
        },
        "28 Sep  2017": {
            "v": "18",
            "e": "158865",
            "set": "true",
            "uri": "v=18&e=158865&set=true"
        },
        "25 Sep  2017": {
            "v": "18",
            "e": "158862",
            "set": "true",
            "uri": "v=18&e=158862&set=true"
        },
        "21 Sep  2017": {
            "v": "18",
            "e": "158858",
            "set": "true",
            "uri": "v=18&e=158858&set=true"
        },
        "18 Sep  2017": {
            "v": "18",
            "e": "158855",
            "set": "true",
            "uri": "v=18&e=158855&set=true"
        },
        "28 Aug  2017": {
            "v": "18",
            "e": "158835",
            "set": "true",
            "uri": "v=18&e=158835&set=true"
        }
    },
    "tag-fifa-17": {
        "20 Sep  2017": {
            "v": "17",
            "e": "158857",
            "set": "true",
            "uri": "v=17&e=158857&set=true"
        },
        "18 Sep  2017": {
            "v": "17",
            "e": "158855",
            "set": "true",
            "uri": "v=17&e=158855&set=true"
        },
        "13 Sep  2017": {
            "v": "17",
            "e": "158850",
            "set": "true",
            "uri": "v=17&e=158850&set=true"
        },
        "11 Sep  2017": {
            "v": "17",
            "e": "158848",
            "set": "true",
            "uri": "v=17&e=158848&set=true"
        },
        "07 Sep  2017": {
            "v": "17",
            "e": "158844",
            "set": "true",
            "uri": "v=17&e=158844&set=true"
        },
        "04 Sep  2017": {
            "v": "17",
            "e": "158841",
            "set": "true",
            "uri": "v=17&e=158841&set=true"
        },
        "31 Aug  2017": {
            "v": "17",
            "e": "158837",
            "set": "true",
            "uri": "v=17&e=158837&set=true"
        },
        "28 Aug  2017": {
            "v": "17",
            "e": "158834",
            "set": "true",
            "uri": "v=17&e=158834&set=true"
        },
        "24 Aug  2017": {
            "v": "17",
            "e": "158830",
            "set": "true",
            "uri": "v=17&e=158830&set=true"
        },
        "22 Aug  2017": {
            "v": "17",
            "e": "158828",
            "set": "true",
            "uri": "v=17&e=158828&set=true"
        },
        "17 Aug  2017": {
            "v": "17",
            "e": "158823",
            "set": "true",
            "uri": "v=17&e=158823&set=true"
        },
        "14 Aug  2017": {
            "v": "17",
            "e": "158820",
            "set": "true",
            "uri": "v=17&e=158820&set=true"
        },
        "10 Aug  2017": {
            "v": "17",
            "e": "158816",
            "set": "true",
            "uri": "v=17&e=158816&set=true"
        },
        "03 Aug  2017": {
            "v": "17",
            "e": "158809",
            "set": "true",
            "uri": "v=17&e=158809&set=true"
        },
        "31 Jul  2017": {
            "v": "17",
            "e": "158806",
            "set": "true",
            "uri": "v=17&e=158806&set=true"
        },
        "27 Jul  2017": {
            "v": "17",
            "e": "158802",
            "set": "true",
            "uri": "v=17&e=158802&set=true"
        },
        "24 Jul  2017": {
            "v": "17",
            "e": "158799",
            "set": "true",
            "uri": "v=17&e=158799&set=true"
        },
        "20 Jul  2017": {
            "v": "17",
            "e": "158795",
            "set": "true",
            "uri": "v=17&e=158795&set=true"
        },
        "17 Jul  2017": {
            "v": "17",
            "e": "158792",
            "set": "true",
            "uri": "v=17&e=158792&set=true"
        },
        "13 Jul  2017": {
            "v": "17",
            "e": "158788",
            "set": "true",
            "uri": "v=17&e=158788&set=true"
        },
        "10 Jul  2017": {
            "v": "17",
            "e": "158785",
            "set": "true",
            "uri": "v=17&e=158785&set=true"
        },
        "06 Jul  2017": {
            "v": "17",
            "e": "158781",
            "set": "true",
            "uri": "v=17&e=158781&set=true"
        },
        "03 Jul  2017": {
            "v": "17",
            "e": "158778",
            "set": "true",
            "uri": "v=17&e=158778&set=true"
        },
        "29 Jun  2017": {
            "v": "17",
            "e": "158774",
            "set": "true",
            "uri": "v=17&e=158774&set=true"
        },
        "26 Jun  2017": {
            "v": "17",
            "e": "158771",
            "set": "true",
            "uri": "v=17&e=158771&set=true"
        },
        "22 Jun  2017": {
            "v": "17",
            "e": "158767",
            "set": "true",
            "uri": "v=17&e=158767&set=true"
        },
        "19 Jun  2017": {
            "v": "17",
            "e": "158764",
            "set": "true",
            "uri": "v=17&e=158764&set=true"
        },
        "14 Jun  2017": {
            "v": "17",
            "e": "158759",
            "set": "true",
            "uri": "v=17&e=158759&set=true"
        },
        "12 Jun  2017": {
            "v": "17",
            "e": "158757",
            "set": "true",
            "uri": "v=17&e=158757&set=true"
        },
        "08 Jun  2017": {
            "v": "17",
            "e": "158753",
            "set": "true",
            "uri": "v=17&e=158753&set=true"
        },
        "06 Jun  2017": {
            "v": "17",
            "e": "158751",
            "set": "true",
            "uri": "v=17&e=158751&set=true"
        },
        "01 Jun  2017": {
            "v": "17",
            "e": "158746",
            "set": "true",
            "uri": "v=17&e=158746&set=true"
        },
        "29 May  2017": {
            "v": "17",
            "e": "158743",
            "set": "true",
            "uri": "v=17&e=158743&set=true"
        },
        "25 May  2017": {
            "v": "17",
            "e": "158739",
            "set": "true",
            "uri": "v=17&e=158739&set=true"
        },
        "22 May  2017": {
            "v": "17",
            "e": "158736",
            "set": "true",
            "uri": "v=17&e=158736&set=true"
        },
        "18 May  2017": {
            "v": "17",
            "e": "158732",
            "set": "true",
            "uri": "v=17&e=158732&set=true"
        },
        "15 May  2017": {
            "v": "17",
            "e": "158729",
            "set": "true",
            "uri": "v=17&e=158729&set=true"
        },
        "11 May  2017": {
            "v": "17",
            "e": "158725",
            "set": "true",
            "uri": "v=17&e=158725&set=true"
        },
        "08 May  2017": {
            "v": "17",
            "e": "158722",
            "set": "true",
            "uri": "v=17&e=158722&set=true"
        },
        "04 May  2017": {
            "v": "17",
            "e": "158718",
            "set": "true",
            "uri": "v=17&e=158718&set=true"
        },
        "02 May  2017": {
            "v": "17",
            "e": "158716",
            "set": "true",
            "uri": "v=17&e=158716&set=true"
        },
        "27 Apr  2017": {
            "v": "17",
            "e": "158711",
            "set": "true",
            "uri": "v=17&e=158711&set=true"
        },
        "24 Apr  2017": {
            "v": "17",
            "e": "158708",
            "set": "true",
            "uri": "v=17&e=158708&set=true"
        },
        "20 Apr  2017": {
            "v": "17",
            "e": "158704",
            "set": "true",
            "uri": "v=17&e=158704&set=true"
        },
        "18 Apr  2017": {
            "v": "17",
            "e": "158702",
            "set": "true",
            "uri": "v=17&e=158702&set=true"
        },
        "13 Apr  2017": {
            "v": "17",
            "e": "158697",
            "set": "true",
            "uri": "v=17&e=158697&set=true"
        },
        "10 Apr  2017": {
            "v": "17",
            "e": "158694",
            "set": "true",
            "uri": "v=17&e=158694&set=true"
        },
        "06 Apr  2017": {
            "v": "17",
            "e": "158690",
            "set": "true",
            "uri": "v=17&e=158690&set=true"
        },
        "03 Apr  2017": {
            "v": "17",
            "e": "158687",
            "set": "true",
            "uri": "v=17&e=158687&set=true"
        },
        "30 Mar  2017": {
            "v": "17",
            "e": "158683",
            "set": "true",
            "uri": "v=17&e=158683&set=true"
        },
        "27 Mar  2017": {
            "v": "17",
            "e": "158680",
            "set": "true",
            "uri": "v=17&e=158680&set=true"
        },
        "23 Mar  2017": {
            "v": "17",
            "e": "158676",
            "set": "true",
            "uri": "v=17&e=158676&set=true"
        },
        "20 Mar  2017": {
            "v": "17",
            "e": "158673",
            "set": "true",
            "uri": "v=17&e=158673&set=true"
        },
        "16 Mar  2017": {
            "v": "17",
            "e": "158669",
            "set": "true",
            "uri": "v=17&e=158669&set=true"
        },
        "13 Mar  2017": {
            "v": "17",
            "e": "158666",
            "set": "true",
            "uri": "v=17&e=158666&set=true"
        },
        "09 Mar  2017": {
            "v": "17",
            "e": "158662",
            "set": "true",
            "uri": "v=17&e=158662&set=true"
        },
        "06 Mar  2017": {
            "v": "17",
            "e": "158659",
            "set": "true",
            "uri": "v=17&e=158659&set=true"
        },
        "02 Mar  2017": {
            "v": "17",
            "e": "158655",
            "set": "true",
            "uri": "v=17&e=158655&set=true"
        },
        "27 Feb  2017": {
            "v": "17",
            "e": "158652",
            "set": "true",
            "uri": "v=17&e=158652&set=true"
        },
        "22 Feb  2017": {
            "v": "17",
            "e": "158647",
            "set": "true",
            "uri": "v=17&e=158647&set=true"
        },
        "20 Feb  2017": {
            "v": "17",
            "e": "158645",
            "set": "true",
            "uri": "v=17&e=158645&set=true"
        },
        "16 Feb  2017": {
            "v": "17",
            "e": "158641",
            "set": "true",
            "uri": "v=17&e=158641&set=true"
        },
        "14 Feb  2017": {
            "v": "17",
            "e": "158639",
            "set": "true",
            "uri": "v=17&e=158639&set=true"
        },
        "09 Feb  2017": {
            "v": "17",
            "e": "158634",
            "set": "true",
            "uri": "v=17&e=158634&set=true"
        },
        "06 Feb  2017": {
            "v": "17",
            "e": "158631",
            "set": "true",
            "uri": "v=17&e=158631&set=true"
        },
        "02 Feb  2017": {
            "v": "17",
            "e": "158627",
            "set": "true",
            "uri": "v=17&e=158627&set=true"
        },
        "30 Jan  2017": {
            "v": "17",
            "e": "158624",
            "set": "true",
            "uri": "v=17&e=158624&set=true"
        },
        "26 Jan  2017": {
            "v": "17",
            "e": "158620",
            "set": "true",
            "uri": "v=17&e=158620&set=true"
        },
        "23 Jan  2017": {
            "v": "17",
            "e": "158617",
            "set": "true",
            "uri": "v=17&e=158617&set=true"
        },
        "19 Jan  2017": {
            "v": "17",
            "e": "158613",
            "set": "true",
            "uri": "v=17&e=158613&set=true"
        },
        "17 Jan  2017": {
            "v": "17",
            "e": "158611",
            "set": "true",
            "uri": "v=17&e=158611&set=true"
        },
        "16 Jan  2017": {
            "v": "17",
            "e": "158610",
            "set": "true",
            "uri": "v=17&e=158610&set=true"
        },
        "12 Jan  2017": {
            "v": "17",
            "e": "158606",
            "set": "true",
            "uri": "v=17&e=158606&set=true"
        },
        "09 Jan  2017": {
            "v": "17",
            "e": "158603",
            "set": "true",
            "uri": "v=17&e=158603&set=true"
        },
        "05 Jan  2017": {
            "v": "17",
            "e": "158599",
            "set": "true",
            "uri": "v=17&e=158599&set=true"
        },
        "03 Jan  2017": {
            "v": "17",
            "e": "158597",
            "set": "true",
            "uri": "v=17&e=158597&set=true"
        },
        "27 Dec  2016": {
            "v": "17",
            "e": "158590",
            "set": "true",
            "uri": "v=17&e=158590&set=true"
        },
        "22 Dec  2016": {
            "v": "17",
            "e": "158585",
            "set": "true",
            "uri": "v=17&e=158585&set=true"
        },
        "19 Dec  2016": {
            "v": "17",
            "e": "158582",
            "set": "true",
            "uri": "v=17&e=158582&set=true"
        },
        "15 Dec  2016": {
            "v": "17",
            "e": "158578",
            "set": "true",
            "uri": "v=17&e=158578&set=true"
        },
        "12 Dec  2016": {
            "v": "17",
            "e": "158575",
            "set": "true",
            "uri": "v=17&e=158575&set=true"
        },
        "08 Dec  2016": {
            "v": "17",
            "e": "158571",
            "set": "true",
            "uri": "v=17&e=158571&set=true"
        },
        "05 Dec  2016": {
            "v": "17",
            "e": "158568",
            "set": "true",
            "uri": "v=17&e=158568&set=true"
        },
        "01 Dec  2016": {
            "v": "17",
            "e": "158564",
            "set": "true",
            "uri": "v=17&e=158564&set=true"
        },
        "28 Nov  2016": {
            "v": "17",
            "e": "158561",
            "set": "true",
            "uri": "v=17&e=158561&set=true"
        },
        "24 Nov  2016": {
            "v": "17",
            "e": "158557",
            "set": "true",
            "uri": "v=17&e=158557&set=true"
        },
        "21 Nov  2016": {
            "v": "17",
            "e": "158554",
            "set": "true",
            "uri": "v=17&e=158554&set=true"
        },
        "17 Nov  2016": {
            "v": "17",
            "e": "158550",
            "set": "true",
            "uri": "v=17&e=158550&set=true"
        },
        "14 Nov  2016": {
            "v": "17",
            "e": "158547",
            "set": "true",
            "uri": "v=17&e=158547&set=true"
        },
        "10 Nov  2016": {
            "v": "17",
            "e": "158543",
            "set": "true",
            "uri": "v=17&e=158543&set=true"
        },
        "07 Nov  2016": {
            "v": "17",
            "e": "158540",
            "set": "true",
            "uri": "v=17&e=158540&set=true"
        },
        "03 Nov  2016": {
            "v": "17",
            "e": "158536",
            "set": "true",
            "uri": "v=17&e=158536&set=true"
        },
        "27 Oct  2016": {
            "v": "17",
            "e": "158529",
            "set": "true",
            "uri": "v=17&e=158529&set=true"
        },
        "19 Oct  2016": {
            "v": "17",
            "e": "158521",
            "set": "true",
            "uri": "v=17&e=158521&set=true"
        },
        "13 Oct  2016": {
            "v": "17",
            "e": "158515",
            "set": "true",
            "uri": "v=17&e=158515&set=true"
        },
        "06 Oct  2016": {
            "v": "17",
            "e": "158508",
            "set": "true",
            "uri": "v=17&e=158508&set=true"
        },
        "29 Sep  2016": {
            "v": "17",
            "e": "158501",
            "set": "true",
            "uri": "v=17&e=158501&set=true"
        },
        "20 Sep  2016": {
            "v": "17",
            "e": "158492",
            "set": "true",
            "uri": "v=17&e=158492&set=true"
        },
        "25 Aug  2016": {
            "v": "17",
            "e": "158466",
            "set": "true",
            "uri": "v=17&e=158466&set=true"
        }
    },
    "tag-fifa-16": {
        "22 Sep  2016": {
            "v": "16",
            "e": "158494",
            "set": "true",
            "uri": "v=16&e=158494&set=true"
        },
        "14 Sep  2016": {
            "v": "16",
            "e": "158486",
            "set": "true",
            "uri": "v=16&e=158486&set=true"
        },
        "08 Sep  2016": {
            "v": "16",
            "e": "158480",
            "set": "true",
            "uri": "v=16&e=158480&set=true"
        },
        "01 Sep  2016": {
            "v": "16",
            "e": "158473",
            "set": "true",
            "uri": "v=16&e=158473&set=true"
        },
        "26 Aug  2016": {
            "v": "16",
            "e": "158467",
            "set": "true",
            "uri": "v=16&e=158467&set=true"
        },
        "18 Aug  2016": {
            "v": "16",
            "e": "158459",
            "set": "true",
            "uri": "v=16&e=158459&set=true"
        },
        "11 Aug  2016": {
            "v": "16",
            "e": "158452",
            "set": "true",
            "uri": "v=16&e=158452&set=true"
        },
        "04 Aug  2016": {
            "v": "16",
            "e": "158445",
            "set": "true",
            "uri": "v=16&e=158445&set=true"
        },
        "28 Jul  2016": {
            "v": "16",
            "e": "158438",
            "set": "true",
            "uri": "v=16&e=158438&set=true"
        },
        "21 Jul  2016": {
            "v": "16",
            "e": "158431",
            "set": "true",
            "uri": "v=16&e=158431&set=true"
        },
        "14 Jul  2016": {
            "v": "16",
            "e": "158424",
            "set": "true",
            "uri": "v=16&e=158424&set=true"
        },
        "07 Jul  2016": {
            "v": "16",
            "e": "158417",
            "set": "true",
            "uri": "v=16&e=158417&set=true"
        },
        "30 Jun  2016": {
            "v": "16",
            "e": "158410",
            "set": "true",
            "uri": "v=16&e=158410&set=true"
        },
        "23 Jun  2016": {
            "v": "16",
            "e": "158403",
            "set": "true",
            "uri": "v=16&e=158403&set=true"
        },
        "16 Jun  2016": {
            "v": "16",
            "e": "158396",
            "set": "true",
            "uri": "v=16&e=158396&set=true"
        },
        "09 Jun  2016": {
            "v": "16",
            "e": "158389",
            "set": "true",
            "uri": "v=16&e=158389&set=true"
        },
        "02 Jun  2016": {
            "v": "16",
            "e": "158382",
            "set": "true",
            "uri": "v=16&e=158382&set=true"
        },
        "26 May  2016": {
            "v": "16",
            "e": "158375",
            "set": "true",
            "uri": "v=16&e=158375&set=true"
        },
        "19 May  2016": {
            "v": "16",
            "e": "158368",
            "set": "true",
            "uri": "v=16&e=158368&set=true"
        },
        "12 May  2016": {
            "v": "16",
            "e": "158361",
            "set": "true",
            "uri": "v=16&e=158361&set=true"
        },
        "05 May  2016": {
            "v": "16",
            "e": "158354",
            "set": "true",
            "uri": "v=16&e=158354&set=true"
        },
        "28 Apr  2016": {
            "v": "16",
            "e": "158347",
            "set": "true",
            "uri": "v=16&e=158347&set=true"
        },
        "21 Apr  2016": {
            "v": "16",
            "e": "158340",
            "set": "true",
            "uri": "v=16&e=158340&set=true"
        },
        "14 Apr  2016": {
            "v": "16",
            "e": "158333",
            "set": "true",
            "uri": "v=16&e=158333&set=true"
        },
        "07 Apr  2016": {
            "v": "16",
            "e": "158326",
            "set": "true",
            "uri": "v=16&e=158326&set=true"
        },
        "31 Mar  2016": {
            "v": "16",
            "e": "158319",
            "set": "true",
            "uri": "v=16&e=158319&set=true"
        },
        "24 Mar  2016": {
            "v": "16",
            "e": "158312",
            "set": "true",
            "uri": "v=16&e=158312&set=true"
        },
        "17 Mar  2016": {
            "v": "16",
            "e": "158305",
            "set": "true",
            "uri": "v=16&e=158305&set=true"
        },
        "10 Mar  2016": {
            "v": "16",
            "e": "158298",
            "set": "true",
            "uri": "v=16&e=158298&set=true"
        },
        "03 Mar  2016": {
            "v": "16",
            "e": "158291",
            "set": "true",
            "uri": "v=16&e=158291&set=true"
        },
        "25 Feb  2016": {
            "v": "16",
            "e": "158284",
            "set": "true",
            "uri": "v=16&e=158284&set=true"
        },
        "19 Feb  2016": {
            "v": "16",
            "e": "158278",
            "set": "true",
            "uri": "v=16&e=158278&set=true"
        },
        "18 Feb  2016": {
            "v": "16",
            "e": "158277",
            "set": "true",
            "uri": "v=16&e=158277&set=true"
        },
        "13 Feb  2016": {
            "v": "16",
            "e": "158272",
            "set": "true",
            "uri": "v=16&e=158272&set=true"
        },
        "11 Feb  2016": {
            "v": "16",
            "e": "158270",
            "set": "true",
            "uri": "v=16&e=158270&set=true"
        },
        "04 Feb  2016": {
            "v": "16",
            "e": "158263",
            "set": "true",
            "uri": "v=16&e=158263&set=true"
        },
        "28 Jan  2016": {
            "v": "16",
            "e": "158256",
            "set": "true",
            "uri": "v=16&e=158256&set=true"
        },
        "21 Jan  2016": {
            "v": "16",
            "e": "158249",
            "set": "true",
            "uri": "v=16&e=158249&set=true"
        },
        "14 Jan  2016": {
            "v": "16",
            "e": "158242",
            "set": "true",
            "uri": "v=16&e=158242&set=true"
        },
        "07 Jan  2016": {
            "v": "16",
            "e": "158235",
            "set": "true",
            "uri": "v=16&e=158235&set=true"
        },
        "30 Dec  2015": {
            "v": "16",
            "e": "158227",
            "set": "true",
            "uri": "v=16&e=158227&set=true"
        },
        "24 Dec  2015": {
            "v": "16",
            "e": "158221",
            "set": "true",
            "uri": "v=16&e=158221&set=true"
        },
        "17 Dec  2015": {
            "v": "16",
            "e": "158214",
            "set": "true",
            "uri": "v=16&e=158214&set=true"
        },
        "10 Dec  2015": {
            "v": "16",
            "e": "158207",
            "set": "true",
            "uri": "v=16&e=158207&set=true"
        },
        "03 Dec  2015": {
            "v": "16",
            "e": "158200",
            "set": "true",
            "uri": "v=16&e=158200&set=true"
        },
        "26 Nov  2015": {
            "v": "16",
            "e": "158193",
            "set": "true",
            "uri": "v=16&e=158193&set=true"
        },
        "19 Nov  2015": {
            "v": "16",
            "e": "158186",
            "set": "true",
            "uri": "v=16&e=158186&set=true"
        },
        "12 Nov  2015": {
            "v": "16",
            "e": "158179",
            "set": "true",
            "uri": "v=16&e=158179&set=true"
        },
        "06 Nov  2015": {
            "v": "16",
            "e": "158173",
            "set": "true",
            "uri": "v=16&e=158173&set=true"
        },
        "30 Oct  2015": {
            "v": "16",
            "e": "158166",
            "set": "true",
            "uri": "v=16&e=158166&set=true"
        },
        "23 Oct  2015": {
            "v": "16",
            "e": "158159",
            "set": "true",
            "uri": "v=16&e=158159&set=true"
        },
        "19 Oct  2015": {
            "v": "16",
            "e": "158155",
            "set": "true",
            "uri": "v=16&e=158155&set=true"
        },
        "16 Oct  2015": {
            "v": "16",
            "e": "158152",
            "set": "true",
            "uri": "v=16&e=158152&set=true"
        },
        "09 Oct  2015": {
            "v": "16",
            "e": "158145",
            "set": "true",
            "uri": "v=16&e=158145&set=true"
        },
        "02 Oct  2015": {
            "v": "16",
            "e": "158138",
            "set": "true",
            "uri": "v=16&e=158138&set=true"
        },
        "25 Sep  2015": {
            "v": "16",
            "e": "158131",
            "set": "true",
            "uri": "v=16&e=158131&set=true"
        },
        "21 Sep  2015": {
            "v": "16",
            "e": "158127",
            "set": "true",
            "uri": "v=16&e=158127&set=true"
        },
        "28 Aug  2015": {
            "v": "16",
            "e": "158103",
            "set": "true",
            "uri": "v=16&e=158103&set=true"
        }
    },
    "tag-fifa-15": {
        "10 Sep  2015": {
            "v": "15",
            "e": "158116",
            "set": "true",
            "uri": "v=15&e=158116&set=true"
        },
        "04 Sep  2015": {
            "v": "15",
            "e": "158110",
            "set": "true",
            "uri": "v=15&e=158110&set=true"
        },
        "01 Sep  2015": {
            "v": "15",
            "e": "158107",
            "set": "true",
            "uri": "v=15&e=158107&set=true"
        },
        "27 Aug  2015": {
            "v": "15",
            "e": "158102",
            "set": "true",
            "uri": "v=15&e=158102&set=true"
        },
        "21 Aug  2015": {
            "v": "15",
            "e": "158096",
            "set": "true",
            "uri": "v=15&e=158096&set=true"
        },
        "14 Aug  2015": {
            "v": "15",
            "e": "158089",
            "set": "true",
            "uri": "v=15&e=158089&set=true"
        },
        "07 Aug  2015": {
            "v": "15",
            "e": "158082",
            "set": "true",
            "uri": "v=15&e=158082&set=true"
        },
        "31 Jul  2015": {
            "v": "15",
            "e": "158075",
            "set": "true",
            "uri": "v=15&e=158075&set=true"
        },
        "24 Jul  2015": {
            "v": "15",
            "e": "158068",
            "set": "true",
            "uri": "v=15&e=158068&set=true"
        },
        "16 Jul  2015": {
            "v": "15",
            "e": "158060",
            "set": "true",
            "uri": "v=15&e=158060&set=true"
        },
        "10 Jul  2015": {
            "v": "15",
            "e": "158054",
            "set": "true",
            "uri": "v=15&e=158054&set=true"
        },
        "03 Jul  2015": {
            "v": "15",
            "e": "158047",
            "set": "true",
            "uri": "v=15&e=158047&set=true"
        },
        "26 Jun  2015": {
            "v": "15",
            "e": "158040",
            "set": "true",
            "uri": "v=15&e=158040&set=true"
        },
        "19 Jun  2015": {
            "v": "15",
            "e": "158033",
            "set": "true",
            "uri": "v=15&e=158033&set=true"
        },
        "12 Jun  2015": {
            "v": "15",
            "e": "158026",
            "set": "true",
            "uri": "v=15&e=158026&set=true"
        },
        "05 Jun  2015": {
            "v": "15",
            "e": "158019",
            "set": "true",
            "uri": "v=15&e=158019&set=true"
        },
        "29 May  2015": {
            "v": "15",
            "e": "158012",
            "set": "true",
            "uri": "v=15&e=158012&set=true"
        },
        "22 May  2015": {
            "v": "15",
            "e": "158005",
            "set": "true",
            "uri": "v=15&e=158005&set=true"
        },
        "15 May  2015": {
            "v": "15",
            "e": "157998",
            "set": "true",
            "uri": "v=15&e=157998&set=true"
        },
        "08 May  2015": {
            "v": "15",
            "e": "157991",
            "set": "true",
            "uri": "v=15&e=157991&set=true"
        },
        "01 May  2015": {
            "v": "15",
            "e": "157984",
            "set": "true",
            "uri": "v=15&e=157984&set=true"
        },
        "24 Apr  2015": {
            "v": "15",
            "e": "157977",
            "set": "true",
            "uri": "v=15&e=157977&set=true"
        },
        "17 Apr  2015": {
            "v": "15",
            "e": "157970",
            "set": "true",
            "uri": "v=15&e=157970&set=true"
        },
        "10 Apr  2015": {
            "v": "15",
            "e": "157963",
            "set": "true",
            "uri": "v=15&e=157963&set=true"
        },
        "01 Apr  2015": {
            "v": "15",
            "e": "157954",
            "set": "true",
            "uri": "v=15&e=157954&set=true"
        },
        "27 Mar  2015": {
            "v": "15",
            "e": "157949",
            "set": "true",
            "uri": "v=15&e=157949&set=true"
        },
        "20 Mar  2015": {
            "v": "15",
            "e": "157942",
            "set": "true",
            "uri": "v=15&e=157942&set=true"
        },
        "13 Mar  2015": {
            "v": "15",
            "e": "157935",
            "set": "true",
            "uri": "v=15&e=157935&set=true"
        },
        "10 Mar  2015": {
            "v": "15",
            "e": "157932",
            "set": "true",
            "uri": "v=15&e=157932&set=true"
        },
        "06 Mar  2015": {
            "v": "15",
            "e": "157928",
            "set": "true",
            "uri": "v=15&e=157928&set=true"
        },
        "27 Feb  2015": {
            "v": "15",
            "e": "157921",
            "set": "true",
            "uri": "v=15&e=157921&set=true"
        },
        "20 Feb  2015": {
            "v": "15",
            "e": "157914",
            "set": "true",
            "uri": "v=15&e=157914&set=true"
        },
        "13 Feb  2015": {
            "v": "15",
            "e": "157907",
            "set": "true",
            "uri": "v=15&e=157907&set=true"
        },
        "06 Feb  2015": {
            "v": "15",
            "e": "157900",
            "set": "true",
            "uri": "v=15&e=157900&set=true"
        },
        "30 Jan  2015": {
            "v": "15",
            "e": "157893",
            "set": "true",
            "uri": "v=15&e=157893&set=true"
        },
        "28 Jan  2015": {
            "v": "15",
            "e": "157891",
            "set": "true",
            "uri": "v=15&e=157891&set=true"
        },
        "26 Jan  2015": {
            "v": "15",
            "e": "157889",
            "set": "true",
            "uri": "v=15&e=157889&set=true"
        },
        "23 Jan  2015": {
            "v": "15",
            "e": "157886",
            "set": "true",
            "uri": "v=15&e=157886&set=true"
        },
        "16 Jan  2015": {
            "v": "15",
            "e": "157879",
            "set": "true",
            "uri": "v=15&e=157879&set=true"
        },
        "09 Jan  2015": {
            "v": "15",
            "e": "157872",
            "set": "true",
            "uri": "v=15&e=157872&set=true"
        },
        "02 Jan  2015": {
            "v": "15",
            "e": "157865",
            "set": "true",
            "uri": "v=15&e=157865&set=true"
        },
        "27 Dec  2014": {
            "v": "15",
            "e": "157859",
            "set": "true",
            "uri": "v=15&e=157859&set=true"
        },
        "19 Dec  2014": {
            "v": "15",
            "e": "157851",
            "set": "true",
            "uri": "v=15&e=157851&set=true"
        },
        "12 Dec  2014": {
            "v": "15",
            "e": "157844",
            "set": "true",
            "uri": "v=15&e=157844&set=true"
        },
        "05 Dec  2014": {
            "v": "15",
            "e": "157837",
            "set": "true",
            "uri": "v=15&e=157837&set=true"
        },
        "28 Nov  2014": {
            "v": "15",
            "e": "157830",
            "set": "true",
            "uri": "v=15&e=157830&set=true"
        },
        "26 Nov  2014": {
            "v": "15",
            "e": "157828",
            "set": "true",
            "uri": "v=15&e=157828&set=true"
        },
        "21 Nov  2014": {
            "v": "15",
            "e": "157823",
            "set": "true",
            "uri": "v=15&e=157823&set=true"
        },
        "14 Nov  2014": {
            "v": "15",
            "e": "157816",
            "set": "true",
            "uri": "v=15&e=157816&set=true"
        },
        "07 Nov  2014": {
            "v": "15",
            "e": "157809",
            "set": "true",
            "uri": "v=15&e=157809&set=true"
        },
        "31 Oct  2014": {
            "v": "15",
            "e": "157802",
            "set": "true",
            "uri": "v=15&e=157802&set=true"
        },
        "24 Oct  2014": {
            "v": "15",
            "e": "157795",
            "set": "true",
            "uri": "v=15&e=157795&set=true"
        },
        "17 Oct  2014": {
            "v": "15",
            "e": "157788",
            "set": "true",
            "uri": "v=15&e=157788&set=true"
        },
        "10 Oct  2014": {
            "v": "15",
            "e": "157781",
            "set": "true",
            "uri": "v=15&e=157781&set=true"
        },
        "02 Oct  2014": {
            "v": "15",
            "e": "157773",
            "set": "true",
            "uri": "v=15&e=157773&set=true"
        },
        "26 Sep  2014": {
            "v": "15",
            "e": "157767",
            "set": "true",
            "uri": "v=15&e=157767&set=true"
        },
        "23 Sep  2014": {
            "v": "15",
            "e": "157764",
            "set": "true",
            "uri": "v=15&e=157764&set=true"
        },
        "18 Sep  2014": {
            "v": "15",
            "e": "157759",
            "set": "true",
            "uri": "v=15&e=157759&set=true"
        },
        "29 Aug  2014": {
            "v": "15",
            "e": "157739",
            "set": "true",
            "uri": "v=15&e=157739&set=true"
        }
    },
    "tag-fifa-14": {
        "19 Sep  2014": {
            "v": "14",
            "e": "157760",
            "set": "true",
            "uri": "v=14&e=157760&set=true"
        },
        "12 Sep  2014": {
            "v": "14",
            "e": "157753",
            "set": "true",
            "uri": "v=14&e=157753&set=true"
        },
        "05 Sep  2014": {
            "v": "14",
            "e": "157746",
            "set": "true",
            "uri": "v=14&e=157746&set=true"
        },
        "29 Aug  2014": {
            "v": "14",
            "e": "157739",
            "set": "true",
            "uri": "v=14&e=157739&set=true"
        },
        "22 Aug  2014": {
            "v": "14",
            "e": "157732",
            "set": "true",
            "uri": "v=14&e=157732&set=true"
        },
        "15 Aug  2014": {
            "v": "14",
            "e": "157725",
            "set": "true",
            "uri": "v=14&e=157725&set=true"
        },
        "08 Aug  2014": {
            "v": "14",
            "e": "157718",
            "set": "true",
            "uri": "v=14&e=157718&set=true"
        },
        "01 Aug  2014": {
            "v": "14",
            "e": "157711",
            "set": "true",
            "uri": "v=14&e=157711&set=true"
        },
        "25 Jul  2014": {
            "v": "14",
            "e": "157704",
            "set": "true",
            "uri": "v=14&e=157704&set=true"
        },
        "20 Jul  2014": {
            "v": "14",
            "e": "157699",
            "set": "true",
            "uri": "v=14&e=157699&set=true"
        },
        "18 Jul  2014": {
            "v": "14",
            "e": "157697",
            "set": "true",
            "uri": "v=14&e=157697&set=true"
        },
        "20 Jun  2014": {
            "v": "14",
            "e": "157669",
            "set": "true",
            "uri": "v=14&e=157669&set=true"
        },
        "13 Jun  2014": {
            "v": "14",
            "e": "157662",
            "set": "true",
            "uri": "v=14&e=157662&set=true"
        },
        "06 Jun  2014": {
            "v": "14",
            "e": "157655",
            "set": "true",
            "uri": "v=14&e=157655&set=true"
        },
        "30 May  2014": {
            "v": "14",
            "e": "157648",
            "set": "true",
            "uri": "v=14&e=157648&set=true"
        },
        "23 May  2014": {
            "v": "14",
            "e": "157641",
            "set": "true",
            "uri": "v=14&e=157641&set=true"
        },
        "16 May  2014": {
            "v": "14",
            "e": "157634",
            "set": "true",
            "uri": "v=14&e=157634&set=true"
        },
        "09 May  2014": {
            "v": "14",
            "e": "157627",
            "set": "true",
            "uri": "v=14&e=157627&set=true"
        },
        "02 May  2014": {
            "v": "14",
            "e": "157620",
            "set": "true",
            "uri": "v=14&e=157620&set=true"
        },
        "25 Apr  2014": {
            "v": "14",
            "e": "157613",
            "set": "true",
            "uri": "v=14&e=157613&set=true"
        },
        "18 Apr  2014": {
            "v": "14",
            "e": "157606",
            "set": "true",
            "uri": "v=14&e=157606&set=true"
        },
        "11 Apr  2014": {
            "v": "14",
            "e": "157599",
            "set": "true",
            "uri": "v=14&e=157599&set=true"
        },
        "04 Apr  2014": {
            "v": "14",
            "e": "157592",
            "set": "true",
            "uri": "v=14&e=157592&set=true"
        },
        "28 Mar  2014": {
            "v": "14",
            "e": "157585",
            "set": "true",
            "uri": "v=14&e=157585&set=true"
        },
        "21 Mar  2014": {
            "v": "14",
            "e": "157578",
            "set": "true",
            "uri": "v=14&e=157578&set=true"
        },
        "14 Mar  2014": {
            "v": "14",
            "e": "157571",
            "set": "true",
            "uri": "v=14&e=157571&set=true"
        },
        "07 Mar  2014": {
            "v": "14",
            "e": "157564",
            "set": "true",
            "uri": "v=14&e=157564&set=true"
        },
        "28 Feb  2014": {
            "v": "14",
            "e": "157557",
            "set": "true",
            "uri": "v=14&e=157557&set=true"
        },
        "21 Feb  2014": {
            "v": "14",
            "e": "157550",
            "set": "true",
            "uri": "v=14&e=157550&set=true"
        },
        "14 Feb  2014": {
            "v": "14",
            "e": "157543",
            "set": "true",
            "uri": "v=14&e=157543&set=true"
        },
        "07 Feb  2014": {
            "v": "14",
            "e": "157536",
            "set": "true",
            "uri": "v=14&e=157536&set=true"
        },
        "31 Jan  2014": {
            "v": "14",
            "e": "157529",
            "set": "true",
            "uri": "v=14&e=157529&set=true"
        },
        "24 Jan  2014": {
            "v": "14",
            "e": "157522",
            "set": "true",
            "uri": "v=14&e=157522&set=true"
        },
        "17 Jan  2014": {
            "v": "14",
            "e": "157515",
            "set": "true",
            "uri": "v=14&e=157515&set=true"
        },
        "10 Jan  2014": {
            "v": "14",
            "e": "157508",
            "set": "true",
            "uri": "v=14&e=157508&set=true"
        },
        "03 Jan  2014": {
            "v": "14",
            "e": "157501",
            "set": "true",
            "uri": "v=14&e=157501&set=true"
        },
        "27 Dec  2013": {
            "v": "14",
            "e": "157494",
            "set": "true",
            "uri": "v=14&e=157494&set=true"
        },
        "20 Dec  2013": {
            "v": "14",
            "e": "157487",
            "set": "true",
            "uri": "v=14&e=157487&set=true"
        },
        "13 Dec  2013": {
            "v": "14",
            "e": "157480",
            "set": "true",
            "uri": "v=14&e=157480&set=true"
        },
        "06 Dec  2013": {
            "v": "14",
            "e": "157473",
            "set": "true",
            "uri": "v=14&e=157473&set=true"
        },
        "29 Nov  2013": {
            "v": "14",
            "e": "157466",
            "set": "true",
            "uri": "v=14&e=157466&set=true"
        },
        "22 Nov  2013": {
            "v": "14",
            "e": "157459",
            "set": "true",
            "uri": "v=14&e=157459&set=true"
        },
        "15 Nov  2013": {
            "v": "14",
            "e": "157452",
            "set": "true",
            "uri": "v=14&e=157452&set=true"
        },
        "08 Nov  2013": {
            "v": "14",
            "e": "157445",
            "set": "true",
            "uri": "v=14&e=157445&set=true"
        },
        "01 Nov  2013": {
            "v": "14",
            "e": "157438",
            "set": "true",
            "uri": "v=14&e=157438&set=true"
        },
        "25 Oct  2013": {
            "v": "14",
            "e": "157431",
            "set": "true",
            "uri": "v=14&e=157431&set=true"
        },
        "18 Oct  2013": {
            "v": "14",
            "e": "157424",
            "set": "true",
            "uri": "v=14&e=157424&set=true"
        },
        "11 Oct  2013": {
            "v": "14",
            "e": "157417",
            "set": "true",
            "uri": "v=14&e=157417&set=true"
        },
        "04 Oct  2013": {
            "v": "14",
            "e": "157410",
            "set": "true",
            "uri": "v=14&e=157410&set=true"
        },
        "27 Sep  2013": {
            "v": "14",
            "e": "157403",
            "set": "true",
            "uri": "v=14&e=157403&set=true"
        },
        "20 Sep  2013": {
            "v": "14",
            "e": "157396",
            "set": "true",
            "uri": "v=14&e=157396&set=true"
        },
        "31 Aug  2013": {
            "v": "14",
            "e": "157376",
            "set": "true",
            "uri": "v=14&e=157376&set=true"
        }
    },
    "tag-fifa-13": {
        "20 Sep  2013": {
            "v": "13",
            "e": "157396",
            "set": "true",
            "uri": "v=13&e=157396&set=true"
        },
        "13 Sep  2013": {
            "v": "13",
            "e": "157389",
            "set": "true",
            "uri": "v=13&e=157389&set=true"
        },
        "06 Sep  2013": {
            "v": "13",
            "e": "157382",
            "set": "true",
            "uri": "v=13&e=157382&set=true"
        },
        "30 Aug  2013": {
            "v": "13",
            "e": "157375",
            "set": "true",
            "uri": "v=13&e=157375&set=true"
        },
        "23 Aug  2013": {
            "v": "13",
            "e": "157368",
            "set": "true",
            "uri": "v=13&e=157368&set=true"
        },
        "16 Aug  2013": {
            "v": "13",
            "e": "157361",
            "set": "true",
            "uri": "v=13&e=157361&set=true"
        },
        "09 Aug  2013": {
            "v": "13",
            "e": "157354",
            "set": "true",
            "uri": "v=13&e=157354&set=true"
        },
        "02 Aug  2013": {
            "v": "13",
            "e": "157347",
            "set": "true",
            "uri": "v=13&e=157347&set=true"
        },
        "26 Jul  2013": {
            "v": "13",
            "e": "157340",
            "set": "true",
            "uri": "v=13&e=157340&set=true"
        },
        "19 Jul  2013": {
            "v": "13",
            "e": "157333",
            "set": "true",
            "uri": "v=13&e=157333&set=true"
        },
        "12 Jul  2013": {
            "v": "13",
            "e": "157326",
            "set": "true",
            "uri": "v=13&e=157326&set=true"
        },
        "05 Jul  2013": {
            "v": "13",
            "e": "157319",
            "set": "true",
            "uri": "v=13&e=157319&set=true"
        },
        "28 Jun  2013": {
            "v": "13",
            "e": "157312",
            "set": "true",
            "uri": "v=13&e=157312&set=true"
        },
        "21 Jun  2013": {
            "v": "13",
            "e": "157305",
            "set": "true",
            "uri": "v=13&e=157305&set=true"
        },
        "14 Jun  2013": {
            "v": "13",
            "e": "157298",
            "set": "true",
            "uri": "v=13&e=157298&set=true"
        },
        "07 Jun  2013": {
            "v": "13",
            "e": "157291",
            "set": "true",
            "uri": "v=13&e=157291&set=true"
        },
        "31 May  2013": {
            "v": "13",
            "e": "157284",
            "set": "true",
            "uri": "v=13&e=157284&set=true"
        },
        "24 May  2013": {
            "v": "13",
            "e": "157277",
            "set": "true",
            "uri": "v=13&e=157277&set=true"
        },
        "17 May  2013": {
            "v": "13",
            "e": "157270",
            "set": "true",
            "uri": "v=13&e=157270&set=true"
        },
        "10 May  2013": {
            "v": "13",
            "e": "157263",
            "set": "true",
            "uri": "v=13&e=157263&set=true"
        },
        "03 May  2013": {
            "v": "13",
            "e": "157256",
            "set": "true",
            "uri": "v=13&e=157256&set=true"
        },
        "26 Apr  2013": {
            "v": "13",
            "e": "157249",
            "set": "true",
            "uri": "v=13&e=157249&set=true"
        },
        "19 Apr  2013": {
            "v": "13",
            "e": "157242",
            "set": "true",
            "uri": "v=13&e=157242&set=true"
        },
        "12 Apr  2013": {
            "v": "13",
            "e": "157235",
            "set": "true",
            "uri": "v=13&e=157235&set=true"
        },
        "05 Apr  2013": {
            "v": "13",
            "e": "157228",
            "set": "true",
            "uri": "v=13&e=157228&set=true"
        },
        "28 Mar  2013": {
            "v": "13",
            "e": "157220",
            "set": "true",
            "uri": "v=13&e=157220&set=true"
        },
        "22 Mar  2013": {
            "v": "13",
            "e": "157214",
            "set": "true",
            "uri": "v=13&e=157214&set=true"
        },
        "15 Mar  2013": {
            "v": "13",
            "e": "157207",
            "set": "true",
            "uri": "v=13&e=157207&set=true"
        },
        "08 Mar  2013": {
            "v": "13",
            "e": "157200",
            "set": "true",
            "uri": "v=13&e=157200&set=true"
        },
        "04 Mar  2013": {
            "v": "13",
            "e": "157196",
            "set": "true",
            "uri": "v=13&e=157196&set=true"
        },
        "01 Mar  2013": {
            "v": "13",
            "e": "157193",
            "set": "true",
            "uri": "v=13&e=157193&set=true"
        },
        "22 Feb  2013": {
            "v": "13",
            "e": "157186",
            "set": "true",
            "uri": "v=13&e=157186&set=true"
        },
        "15 Feb  2013": {
            "v": "13",
            "e": "157179",
            "set": "true",
            "uri": "v=13&e=157179&set=true"
        },
        "31 Aug  2012": {
            "v": "13",
            "e": "157011",
            "set": "true",
            "uri": "v=13&e=157011&set=true"
        }
    },
    "tag-fifa-12": {
        "22 Feb  2012": {
            "v": "12",
            "e": "156820",
            "set": "true",
            "uri": "v=12&e=156820&set=true"
        },
        "30 Aug  2011": {
            "v": "12",
            "e": "156644",
            "set": "true",
            "uri": "v=12&e=156644&set=true"
        }
    },
    "tag-fifa-11": {
        "22 Feb  2011": {
            "v": "11",
            "e": "156455",
            "set": "true",
            "uri": "v=11&e=156455&set=true"
        },
        "30 Aug  2010": {
            "v": "11",
            "e": "156279",
            "set": "true",
            "uri": "v=11&e=156279&set=true"
        }
    },
    "tag-fifa-10": {
        "22 Feb  2010": {
            "v": "10",
            "e": "156090",
            "set": "true",
            "uri": "v=10&e=156090&set=true"
        },
        "30 Aug  2009": {
            "v": "10",
            "e": "155914",
            "set": "true",
            "uri": "v=10&e=155914&set=true"
        }
    },
    "tag-fifa-09": {
        "22 Feb  2009": {
            "v": "09",
            "e": "155725",
            "set": "true",
            "uri": "v=09&e=155725&set=true"
        },
        "30 Aug  2008": {
            "v": "09",
            "e": "155549",
            "set": "true",
            "uri": "v=09&e=155549&set=true"
        }
    },
    "tag-fifa-08": {
        "22 Feb  2008": {
            "v": "08",
            "e": "155359",
            "set": "true",
            "uri": "v=08&e=155359&set=true"
        },
        "30 Aug  2007": {
            "v": "08",
            "e": "155183",
            "set": "true",
            "uri": "v=08&e=155183&set=true"
        }
    },
    "tag-fifa-07": {
        "22 Feb  2007": {
            "v": "07",
            "e": "154994",
            "set": "true",
            "uri": "v=07&e=154994&set=true"
        },
        "30 Aug  2006": {
            "v": "07",
            "e": "154818",
            "set": "true",
            "uri": "v=07&e=154818&set=true"
        }
    },
    "_version": "25-04-2019 14:15:15"
}